pyfastnoisesimd/__init__.py
pyfastnoisesimd/extension.cp36-win32.pyd
pyfastnoisesimd/helpers.py
pyfastnoisesimd/test_fns.py
pyfastnoisesimd/version.py
pyfastnoisesimd-0.4.2.dist-info/LICENSE
pyfastnoisesimd-0.4.2.dist-info/METADATA
pyfastnoisesimd-0.4.2.dist-info/WHEEL
pyfastnoisesimd-0.4.2.dist-info/top_level.txt
pyfastnoisesimd-0.4.2.dist-info/RECORD
