Metadata-Version: 2.1
Name: pyfastnoisesimd
Version: 0.4.2
Summary: Python Fast Noise with SIMD
Home-page: http://github.com/robbmcleod/pyfastnoisesimd
Author: Robert A. McLeod
Author-email: robbmcleod@gmail.com
Maintainer: Robert A. McLeod
Maintainer-email: robbmcleod@gmail.com
License: https://opensource.org/licenses/BSD-3-Clause
Platform: any
Classifier: Development Status :: 5 - Production/Stable
Classifier: Intended Audience :: Developers
Classifier: Intended Audience :: Information Technology
Classifier: License :: OSI Approved :: BSD License
Classifier: Programming Language :: Python
Classifier: Programming Language :: Python :: 3.6
Classifier: Programming Language :: Python :: 3.7
Classifier: Programming Language :: Python :: 3.8
Classifier: Programming Language :: Python :: 3.9
Classifier: Topic :: Software Development :: Libraries :: Python Modules
Classifier: Topic :: Multimedia :: Graphics :: 3D Modeling
Classifier: Operating System :: Microsoft :: Windows
Classifier: Operating System :: Unix
